{
  "user": [
    {
      "id": "0",
      "userId": "a",
      "pwd": "a",
      "name": "a"
    },
    {
      "id": "1",
      "userId": "b",
      "pwd": "a",
      "name": "b"
    },
    {
      "id": 2,
      "userId": "c",
      "pwd": "c",
      "name": "c"
    }
  ],
  "data": [
    {
      "id": "1",
      "type": "expenses",
      "date": "1/30/2024",
      "amount": 87800735,
      "category": "문화생활",
      "asset": "현금",
      "content": "Sed ante. Vivamus tortor. Duis mattis egestas metus.\n\nAenean fermentum. Donec ut mauris eget massa tempor convallis. Nulla neque libero, convallis eget, eleifend luctus, ultricies eu, nibh."
    },
    {
      "id": "2",
      "type": "expenses",
      "date": "2/22/2024",
      "amount": 33537955,
      "category": "패션/미용",
      "asset": "우리은행",
      "content": "Aenean lectus. Pellentesque eget nunc. Donec quis orci eget orci vehicula condimentum.\n\nCurabitur in libero ut massa volutpat convallis. Morbi odio odio, elementum eu, interdum eu, tincidunt in, leo. Maecenas pulvinar lobortis est."
    },
    {
      "id": "3",
      "type": "expenses",
      "date": "10/25/2023",
      "amount": 28223486,
      "category": "식비",
      "asset": "국민은행",
      "content": "Pellentesque at nulla. Suspendisse potenti. Cras in purus eu magna vulputate luctus."
    },
    {
      "id": "4",
      "type": "expenses",
      "date": "10/19/2023",
      "amount": 34977084,
      "category": "마트/편의점",
      "asset": "국민은행",
      "content": "Vestibulum quam sapien, varius ut, blandit non, interdum in, ante. Vestibulum ante ipsum primis in faucibus orci luctus et ultrices posuere cubilia Curae; Duis faucibus accumsan odio. Curabitur convallis."
    },
    {
      "id": "5",
      "type": "income",
      "date": "11/12/2023",
      "amount": 25955435,
      "category": "건강",
      "asset": "국민은행",
      "content": "Lorem ipsum dolor sit amet, consectetuer adipiscing elit. Proin risus. Praesent lectus.\n\nVestibulum quam sapien, varius ut, blandit non, interdum in, ante. Vestibulum ante ipsum primis in faucibus orci luctus et ultrices posuere cubilia Curae; Duis faucibus accumsan odio. Curabitur convallis."
    },
    {
      "id": "6",
      "type": "expenses",
      "date": "11/30/2023",
      "amount": 18353751,
      "category": "경조사/회비",
      "asset": "국민은행",
      "content": "Maecenas leo odio, condimentum id, luctus nec, molestie sed, justo. Pellentesque viverra pede ac diam. Cras pellentesque volutpat dui."
    },
    {
      "id": "7",
      "type": "income",
      "date": "8/29/2023",
      "amount": 31086232,
      "category": "기타",
      "asset": "우리은행",
      "content": "Quisque id justo sit amet sapien dignissim vestibulum. Vestibulum ante ipsum primis in faucibus orci luctus et ultrices posuere cubilia Curae; Nulla dapibus dolor vel est. Donec odio justo, sollicitudin ut, suscipit a, feugiat et, eros.\n\nVestibulum ac est lacinia nisi venenatis tristique. Fusce congue, diam id ornare imperdiet, sapien urna pretium nisl, ut volutpat sapien arcu sed augue. Aliquam erat volutpat."
    },
    {
      "id": "8",
      "type": "income",
      "date": "5/6/2024",
      "amount": 17596220,
      "category": "교통/차량",
      "asset": "우리은행",
      "content": "In congue. Etiam justo. Etiam pretium iaculis justo.\n\nIn hac habitasse platea dictumst. Etiam faucibus cursus urna. Ut tellus."
    },
    {
      "id": "9",
      "type": "income",
      "date": "10/16/2023",
      "amount": 14066950,
      "category": "건강",
      "asset": "우리은행",
      "content": "Phasellus in felis. Donec semper sapien a libero. Nam dui."
    },
    {
      "id": "10",
      "type": "expenses",
      "date": "1/29/2024",
      "amount": 85032604,
      "category": "문화생활",
      "asset": "현금",
      "content": "Pellentesque at nulla. Suspendisse potenti. Cras in purus eu magna vulputate luctus.\n\nCum sociis natoque penatibus et magnis dis parturient montes, nascetur ridiculus mus. Vivamus vestibulum sagittis sapien. Cum sociis natoque penatibus et magnis dis parturient montes, nascetur ridiculus mus."
    },
    {
      "id": "11",
      "type": "expenses",
      "date": "8/31/2023",
      "amount": 25661252,
      "category": "주거/통신",
      "asset": "현금",
      "content": "Vestibulum ac est lacinia nisi venenatis tristique. Fusce congue, diam id ornare imperdiet, sapien urna pretium nisl, ut volutpat sapien arcu sed augue. Aliquam erat volutpat.\n\nIn congue. Etiam justo. Etiam pretium iaculis justo."
    },
    {
      "id": "12",
      "type": "expenses",
      "date": "11/8/2023",
      "amount": 33372489,
      "category": "교통/차량",
      "asset": "현금",
      "content": "Curabitur in libero ut massa volutpat convallis. Morbi odio odio, elementum eu, interdum eu, tincidunt in, leo. Maecenas pulvinar lobortis est."
    },
    {
      "id": "13",
      "type": "expenses",
      "date": "4/2/2024",
      "amount": 17235425,
      "category": "식비",
      "asset": "우리은행",
      "content": "Vestibulum quam sapien, varius ut, blandit non, interdum in, ante. Vestibulum ante ipsum primis in faucibus orci luctus et ultrices posuere cubilia Curae; Duis faucibus accumsan odio. Curabitur convallis.\n\nDuis consequat dui nec nisi volutpat eleifend. Donec ut dolor. Morbi vel lectus in quam fringilla rhoncus."
    },
    {
      "id": "14",
      "type": "expenses",
      "date": "5/7/2024",
      "amount": 73475345,
      "category": "건강",
      "asset": "국민은행",
      "content": "Phasellus sit amet erat. Nulla tempus. Vivamus in felis eu sapien cursus vestibulum.\n\nProin eu mi. Nulla ac enim. In tempor, turpis nec euismod scelerisque, quam turpis adipiscing lorem, vitae mattis nibh ligula nec sem."
    },
    {
      "id": "15",
      "type": "income",
      "date": "12/27/2023",
      "amount": 72736981,
      "category": "식비",
      "asset": "현금",
      "content": "Lorem ipsum dolor sit amet, consectetuer adipiscing elit. Proin risus. Praesent lectus.\n\nVestibulum quam sapien, varius ut, blandit non, interdum in, ante. Vestibulum ante ipsum primis in faucibus orci luctus et ultrices posuere cubilia Curae; Duis faucibus accumsan odio. Curabitur convallis."
    },
    {
      "id": "16",
      "type": "expenses",
      "date": "9/19/2023",
      "amount": 63619188,
      "category": "기타",
      "asset": "국민은행",
      "content": "Proin eu mi. Nulla ac enim. In tempor, turpis nec euismod scelerisque, quam turpis adipiscing lorem, vitae mattis nibh ligula nec sem."
    },
    {
      "id": "17",
      "type": "income",
      "date": "10/18/2023",
      "amount": 34281134,
      "category": "마트/편의점",
      "asset": "국민은행",
      "content": "Curabitur in libero ut massa volutpat convallis. Morbi odio odio, elementum eu, interdum eu, tincidunt in, leo. Maecenas pulvinar lobortis est."
    },
    {
      "id": "18",
      "type": "income",
      "date": "2/16/2024",
      "amount": 78999690,
      "category": "교육",
      "asset": "국민은행",
      "content": "Proin interdum mauris non ligula pellentesque ultrices. Phasellus id sapien in sapien iaculis congue. Vivamus metus arcu, adipiscing molestie, hendrerit at, vulputate vitae, nisl."
    },
    {
      "id": "19",
      "type": "expenses",
      "date": "10/18/2023",
      "amount": 41837758,
      "category": "패션/미용",
      "asset": "국민은행",
      "content": "In congue. Etiam justo. Etiam pretium iaculis justo."
    },
    {
      "id": "20",
      "type": "income",
      "date": "2/20/2024",
      "amount": 77228658,
      "category": "경조사/회비",
      "asset": "현금",
      "content": "Mauris enim leo, rhoncus sed, vestibulum sit amet, cursus id, turpis. Integer aliquet, massa id lobortis convallis, tortor risus dapibus augue, vel accumsan tellus nisi eu orci. Mauris lacinia sapien quis libero.\n\nNullam sit amet turpis elementum ligula vehicula consequat. Morbi a ipsum. Integer a nibh."
    },
    {
      "id": "21",
      "type": "income",
      "date": "1/30/2024",
      "amount": 77096670,
      "category": "생활용품",
      "asset": "국민은행",
      "content": "Integer ac leo. Pellentesque ultrices mattis odio. Donec vitae nisi.\n\nNam ultrices, libero non mattis pulvinar, nulla pede ullamcorper augue, a suscipit nulla elit ac nulla. Sed vel enim sit amet nunc viverra dapibus. Nulla suscipit ligula in lacus."
    },
    {
      "id": "22",
      "type": "expenses",
      "date": "8/2/2023",
      "amount": 84030504,
      "category": "건강",
      "asset": "우리은행",
      "content": "Phasellus in felis. Donec semper sapien a libero. Nam dui.\n\nProin leo odio, porttitor id, consequat in, consequat ut, nulla. Sed accumsan felis. Ut at dolor quis odio consequat varius."
    },
    {
      "id": "23",
      "type": "income",
      "date": "1/10/2024",
      "amount": 79371776,
      "category": "기타",
      "asset": "현금",
      "content": "Nulla ut erat id mauris vulputate elementum. Nullam varius. Nulla facilisi.\n\nCras non velit nec nisi vulputate nonummy. Maecenas tincidunt lacus at velit. Vivamus vel nulla eget eros elementum pellentesque."
    },
    {
      "id": "24",
      "type": "income",
      "date": "4/21/2024",
      "amount": 79581634,
      "category": "식비",
      "asset": "우리은행",
      "content": "Integer ac leo. Pellentesque ultrices mattis odio. Donec vitae nisi.\n\nNam ultrices, libero non mattis pulvinar, nulla pede ullamcorper augue, a suscipit nulla elit ac nulla. Sed vel enim sit amet nunc viverra dapibus. Nulla suscipit ligula in lacus."
    },
    {
      "id": "25",
      "type": "income",
      "date": "12/15/2023",
      "amount": 8173429,
      "category": "교육",
      "asset": "국민은행",
      "content": "Quisque id justo sit amet sapien dignissim vestibulum. Vestibulum ante ipsum primis in faucibus orci luctus et ultrices posuere cubilia Curae; Nulla dapibus dolor vel est. Donec odio justo, sollicitudin ut, suscipit a, feugiat et, eros."
    },
    {
      "id": "26",
      "type": "expenses",
      "date": "5/30/2024",
      "amount": 51952873,
      "category": "기타",
      "asset": "국민은행",
      "content": "Fusce posuere felis sed lacus. Morbi sem mauris, laoreet ut, rhoncus aliquet, pulvinar sed, nisl. Nunc rhoncus dui vel sem.\n\nSed sagittis. Nam congue, risus semper porta volutpat, quam pede lobortis ligula, sit amet eleifend pede libero quis orci. Nullam molestie nibh in lectus."
    },
    {
      "id": "27",
      "type": "expenses",
      "date": "11/12/2023",
      "amount": 66498741,
      "category": "패션/미용",
      "asset": "현금",
      "content": "Mauris enim leo, rhoncus sed, vestibulum sit amet, cursus id, turpis. Integer aliquet, massa id lobortis convallis, tortor risus dapibus augue, vel accumsan tellus nisi eu orci. Mauris lacinia sapien quis libero.\n\nNullam sit amet turpis elementum ligula vehicula consequat. Morbi a ipsum. Integer a nibh."
    },
    {
      "id": "28",
      "type": "income",
      "date": "1/7/2024",
      "amount": 11921399,
      "category": "부모님",
      "asset": "국민은행",
      "content": "Curabitur in libero ut massa volutpat convallis. Morbi odio odio, elementum eu, interdum eu, tincidunt in, leo. Maecenas pulvinar lobortis est.\n\nPhasellus sit amet erat. Nulla tempus. Vivamus in felis eu sapien cursus vestibulum."
    },
    {
      "id": "29",
      "type": "expenses",
      "date": "7/19/2023",
      "amount": 14860327,
      "category": "패션/미용",
      "asset": "현금",
      "content": "Proin interdum mauris non ligula pellentesque ultrices. Phasellus id sapien in sapien iaculis congue. Vivamus metus arcu, adipiscing molestie, hendrerit at, vulputate vitae, nisl."
    },
    {
      "id": "30",
      "type": "expenses",
      "date": "9/5/2023",
      "amount": 58836938,
      "category": "문화생활",
      "asset": "우리은행",
      "content": "Proin interdum mauris non ligula pellentesque ultrices. Phasellus id sapien in sapien iaculis congue. Vivamus metus arcu, adipiscing molestie, hendrerit at, vulputate vitae, nisl."
    },
    {
      "id": "31",
      "type": "expenses",
      "date": "2/2/2024",
      "amount": 75979512,
      "category": "경조사/회비",
      "asset": "우리은행",
      "content": "Aenean fermentum. Donec ut mauris eget massa tempor convallis. Nulla neque libero, convallis eget, eleifend luctus, ultricies eu, nibh.\n\nQuisque id justo sit amet sapien dignissim vestibulum. Vestibulum ante ipsum primis in faucibus orci luctus et ultrices posuere cubilia Curae; Nulla dapibus dolor vel est. Donec odio justo, sollicitudin ut, suscipit a, feugiat et, eros."
    },
    {
      "id": "32",
      "type": "expenses",
      "date": "3/12/2024",
      "amount": 15887685,
      "category": "부모님",
      "asset": "국민은행",
      "content": "Maecenas tristique, est et tempus semper, est quam pharetra magna, ac consequat metus sapien ut nunc. Vestibulum ante ipsum primis in faucibus orci luctus et ultrices posuere cubilia Curae; Mauris viverra diam vitae quam. Suspendisse potenti."
    },
    {
      "id": "33",
      "type": "expenses",
      "date": "5/5/2024",
      "amount": 24542491,
      "category": "문화생활",
      "asset": "국민은행",
      "content": "In congue. Etiam justo. Etiam pretium iaculis justo."
    },
    {
      "id": "34",
      "type": "expenses",
      "date": "3/28/2024",
      "amount": 99701049,
      "category": "교통/차량",
      "asset": "현금",
      "content": "Donec diam neque, vestibulum eget, vulputate ut, ultrices vel, augue. Vestibulum ante ipsum primis in faucibus orci luctus et ultrices posuere cubilia Curae; Donec pharetra, magna vestibulum aliquet ultrices, erat tortor sollicitudin mi, sit amet lobortis sapien sapien non mi. Integer ac neque."
    },
    {
      "id": "35",
      "type": "income",
      "date": "8/18/2023",
      "amount": 51134898,
      "category": "건강",
      "asset": "국민은행",
      "content": "Nulla ut erat id mauris vulputate elementum. Nullam varius. Nulla facilisi."
    },
    {
      "id": "37",
      "type": "income",
      "date": "5/3/2024",
      "amount": 4745460,
      "category": "기타",
      "asset": "은행",
      "content": "Nullam porttitor lacus at turpis. Donec posuere metus vitae ipsum. Aliquam non mauris.\n\nMorbi non lectus. Aliquam sit amet diam in magna bibendum imperdiet. Nullam orci pede, venenatis non, sodales sed, tincidunt eu, felis."
    },
    {
      "id": "38",
      "type": "expenses",
      "date": "4/3/2024",
      "amount": 80268912,
      "category": "마트/편의점",
      "asset": "현금",
      "content": "Nam ultrices, libero non mattis pulvinar, nulla pede ullamcorper augue, a suscipit nulla elit ac nulla. Sed vel enim sit amet nunc viverra dapibus. Nulla suscipit ligula in lacus."
    },
    {
      "id": "39",
      "type": "income",
      "date": "3/31/2024",
      "amount": 8851489,
      "category": "교통/차량",
      "asset": "현금",
      "content": "Donec diam neque, vestibulum eget, vulputate ut, ultrices vel, augue. Vestibulum ante ipsum primis in faucibus orci luctus et ultrices posuere cubilia Curae; Donec pharetra, magna vestibulum aliquet ultrices, erat tortor sollicitudin mi, sit amet lobortis sapien sapien non mi. Integer ac neque.\n\nDuis bibendum. Morbi non quam nec dui luctus rutrum. Nulla tellus."
    },
    {
      "id": "40",
      "type": "expenses",
      "date": "12/20/2023",
      "amount": 5609871,
      "category": "생활용품",
      "asset": "국민은행",
      "content": "Etiam vel augue. Vestibulum rutrum rutrum neque. Aenean auctor gravida sem."
    },
    {
      "id": "41",
      "type": "expenses",
      "date": "6/11/2023",
      "amount": 93312444,
      "category": "교통/차량",
      "asset": "현금",
      "content": "Sed sagittis. Nam congue, risus semper porta volutpat, quam pede lobortis ligula, sit amet eleifend pede libero quis orci. Nullam molestie nibh in lectus."
    },
    {
      "id": "42",
      "type": "income",
      "date": "7/12/2023",
      "amount": 86517227,
      "category": "교육",
      "asset": "국민은행",
      "content": "In quis justo. Maecenas rhoncus aliquam lacus. Morbi quis tortor id nulla ultrices aliquet.\n\nMaecenas leo odio, condimentum id, luctus nec, molestie sed, justo. Pellentesque viverra pede ac diam. Cras pellentesque volutpat dui."
    },
    {
      "id": "43",
      "type": "income",
      "date": "5/27/2024",
      "amount": 92928431,
      "category": "패션/미용",
      "asset": "국민은행",
      "content": "Praesent blandit. Nam nulla. Integer pede justo, lacinia eget, tincidunt eget, tempus vel, pede."
    },
    {
      "id": "44",
      "type": "income",
      "date": "1/8/2024",
      "amount": 67908112,
      "category": "교육",
      "asset": "현금",
      "content": "Curabitur gravida nisi at nibh. In hac habitasse platea dictumst. Aliquam augue quam, sollicitudin vitae, consectetuer eget, rutrum at, lorem."
    },
    {
      "id": "45",
      "type": "income",
      "date": "5/23/2024",
      "amount": 3257667,
      "category": "마트/편의점",
      "asset": "국민은행",
      "content": "Mauris enim leo, rhoncus sed, vestibulum sit amet, cursus id, turpis. Integer aliquet, massa id lobortis convallis, tortor risus dapibus augue, vel accumsan tellus nisi eu orci. Mauris lacinia sapien quis libero."
    },
    {
      "id": "46",
      "type": "income",
      "date": "11/9/2023",
      "amount": 64021488,
      "category": "문화생활",
      "asset": "우리은행",
      "content": "Praesent id massa id nisl venenatis lacinia. Aenean sit amet justo. Morbi ut odio.\n\nCras mi pede, malesuada in, imperdiet et, commodo vulputate, justo. In blandit ultrices enim. Lorem ipsum dolor sit amet, consectetuer adipiscing elit."
    },
    {
      "id": "47",
      "type": "expenses",
      "date": "2/7/2024",
      "amount": 2964279,
      "category": "마트/편의점",
      "asset": "현금",
      "content": "Pellentesque at nulla. Suspendisse potenti. Cras in purus eu magna vulputate luctus.\n\nCum sociis natoque penatibus et magnis dis parturient montes, nascetur ridiculus mus. Vivamus vestibulum sagittis sapien. Cum sociis natoque penatibus et magnis dis parturient montes, nascetur ridiculus mus."
    },
    {
      "id": "48",
      "type": "income",
      "date": "8/19/2023",
      "amount": 19526515,
      "category": "식비",
      "asset": "국민은행",
      "content": "Duis consequat dui nec nisi volutpat eleifend. Donec ut dolor. Morbi vel lectus in quam fringilla rhoncus.\n\nMauris enim leo, rhoncus sed, vestibulum sit amet, cursus id, turpis. Integer aliquet, massa id lobortis convallis, tortor risus dapibus augue, vel accumsan tellus nisi eu orci. Mauris lacinia sapien quis libero."
    },
    {
      "id": "49",
      "type": "expenses",
      "date": "7/24/2023",
      "amount": 89706967,
      "category": "패션/미용",
      "asset": "국민은행",
      "content": "In hac habitasse platea dictumst. Etiam faucibus cursus urna. Ut tellus."
    },
    {
      "id": "50",
      "type": "expenses",
      "date": "7/1/2023",
      "amount": 71642308,
      "category": "경조사/회비",
      "asset": "우리은행",
      "content": "Duis aliquam convallis nunc. Proin at turpis a pede posuere nonummy. Integer non velit."
    },
    {
      "id": "51",
      "type": "expenses",
      "date": "12/2/2023",
      "amount": 1691009,
      "category": "주거/통신",
      "asset": "국민은행",
      "content": "Aenean fermentum. Donec ut mauris eget massa tempor convallis. Nulla neque libero, convallis eget, eleifend luctus, ultricies eu, nibh.\n\nQuisque id justo sit amet sapien dignissim vestibulum. Vestibulum ante ipsum primis in faucibus orci luctus et ultrices posuere cubilia Curae; Nulla dapibus dolor vel est. Donec odio justo, sollicitudin ut, suscipit a, feugiat et, eros."
    },
    {
      "id": "52",
      "type": "expenses",
      "date": "7/8/2023",
      "amount": 51170921,
      "category": "교육",
      "asset": "현금",
      "content": "Curabitur gravida nisi at nibh. In hac habitasse platea dictumst. Aliquam augue quam, sollicitudin vitae, consectetuer eget, rutrum at, lorem."
    },
    {
      "id": "53",
      "type": "expenses",
      "date": "6/18/2023",
      "amount": 49574317,
      "category": "생활용품",
      "asset": "국민은행",
      "content": "Aenean fermentum. Donec ut mauris eget massa tempor convallis. Nulla neque libero, convallis eget, eleifend luctus, ultricies eu, nibh.\n\nQuisque id justo sit amet sapien dignissim vestibulum. Vestibulum ante ipsum primis in faucibus orci luctus et ultrices posuere cubilia Curae; Nulla dapibus dolor vel est. Donec odio justo, sollicitudin ut, suscipit a, feugiat et, eros."
    },
    {
      "id": "54",
      "type": "income",
      "date": "5/9/2024",
      "amount": 48432011,
      "category": "교육",
      "asset": "국민은행",
      "content": "In congue. Etiam justo. Etiam pretium iaculis justo."
    },
    {
      "id": "55",
      "type": "income",
      "date": "6/12/2023",
      "amount": 70664279,
      "category": "부모님",
      "asset": "국민은행",
      "content": "Morbi porttitor lorem id ligula. Suspendisse ornare consequat lectus. In est risus, auctor sed, tristique in, tempus sit amet, sem."
    },
    {
      "id": "56",
      "type": "expenses",
      "date": "9/16/2023",
      "amount": 64620022,
      "category": "건강",
      "asset": "우리은행",
      "content": "Nullam porttitor lacus at turpis. Donec posuere metus vitae ipsum. Aliquam non mauris."
    },
    {
      "id": "57",
      "type": "expenses",
      "date": "12/31/2023",
      "amount": 68338175,
      "category": "생활용품",
      "asset": "현금",
      "content": "Nullam sit amet turpis elementum ligula vehicula consequat. Morbi a ipsum. Integer a nibh.\n\nIn quis justo. Maecenas rhoncus aliquam lacus. Morbi quis tortor id nulla ultrices aliquet."
    },
    {
      "id": "58",
      "type": "expenses",
      "date": "9/8/2023",
      "amount": 45359572,
      "category": "교육",
      "asset": "국민은행",
      "content": "Duis bibendum, felis sed interdum venenatis, turpis enim blandit mi, in porttitor pede justo eu massa. Donec dapibus. Duis at velit eu est congue elementum.\n\nIn hac habitasse platea dictumst. Morbi vestibulum, velit id pretium iaculis, diam erat fermentum justo, nec condimentum neque sapien placerat ante. Nulla justo."
    },
    {
      "id": "59",
      "type": "expenses",
      "date": "12/8/2023",
      "amount": 14735747,
      "category": "마트/편의점",
      "asset": "현금",
      "content": "Praesent blandit. Nam nulla. Integer pede justo, lacinia eget, tincidunt eget, tempus vel, pede."
    },
    {
      "id": "60",
      "type": "income",
      "date": "1/13/2024",
      "amount": 70794073,
      "category": "교육",
      "asset": "국민은행",
      "content": "Fusce posuere felis sed lacus. Morbi sem mauris, laoreet ut, rhoncus aliquet, pulvinar sed, nisl. Nunc rhoncus dui vel sem.\n\nSed sagittis. Nam congue, risus semper porta volutpat, quam pede lobortis ligula, sit amet eleifend pede libero quis orci. Nullam molestie nibh in lectus."
    },
    {
      "id": "61",
      "type": "expenses",
      "date": "2/27/2024",
      "amount": 72099782,
      "category": "식비",
      "asset": "국민은행",
      "content": "Fusce posuere felis sed lacus. Morbi sem mauris, laoreet ut, rhoncus aliquet, pulvinar sed, nisl. Nunc rhoncus dui vel sem.\n\nSed sagittis. Nam congue, risus semper porta volutpat, quam pede lobortis ligula, sit amet eleifend pede libero quis orci. Nullam molestie nibh in lectus."
    },
    {
      "id": "62",
      "type": "expenses",
      "date": "3/4/2024",
      "amount": 54439891,
      "category": "생활용품",
      "asset": "우리은행",
      "content": "Proin leo odio, porttitor id, consequat in, consequat ut, nulla. Sed accumsan felis. Ut at dolor quis odio consequat varius."
    },
    {
      "id": "63",
      "type": "income",
      "date": "9/14/2023",
      "amount": 1985719,
      "category": "경조사/회비",
      "asset": "현금",
      "content": "Etiam vel augue. Vestibulum rutrum rutrum neque. Aenean auctor gravida sem.\n\nPraesent id massa id nisl venenatis lacinia. Aenean sit amet justo. Morbi ut odio."
    },
    {
      "id": "64",
      "type": "expenses",
      "date": "3/3/2024",
      "amount": 30495941,
      "category": "교통/차량",
      "asset": "우리은행",
      "content": "Donec diam neque, vestibulum eget, vulputate ut, ultrices vel, augue. Vestibulum ante ipsum primis in faucibus orci luctus et ultrices posuere cubilia Curae; Donec pharetra, magna vestibulum aliquet ultrices, erat tortor sollicitudin mi, sit amet lobortis sapien sapien non mi. Integer ac neque.\n\nDuis bibendum. Morbi non quam nec dui luctus rutrum. Nulla tellus."
    },
    {
      "id": "65",
      "type": "expenses",
      "date": "3/25/2024",
      "amount": 92866903,
      "category": "주거/통신",
      "asset": "현금",
      "content": "Integer ac leo. Pellentesque ultrices mattis odio. Donec vitae nisi.\n\nNam ultrices, libero non mattis pulvinar, nulla pede ullamcorper augue, a suscipit nulla elit ac nulla. Sed vel enim sit amet nunc viverra dapibus. Nulla suscipit ligula in lacus."
    },
    {
      "id": "66",
      "type": "expenses",
      "date": "1/8/2024",
      "amount": 92765672,
      "category": "생활용품",
      "asset": "현금",
      "content": "Praesent blandit. Nam nulla. Integer pede justo, lacinia eget, tincidunt eget, tempus vel, pede.\n\nMorbi porttitor lorem id ligula. Suspendisse ornare consequat lectus. In est risus, auctor sed, tristique in, tempus sit amet, sem."
    },
    {
      "id": "67",
      "type": "income",
      "date": "12/22/2023",
      "amount": 98775721,
      "category": "부모님",
      "asset": "현금",
      "content": "Sed sagittis. Nam congue, risus semper porta volutpat, quam pede lobortis ligula, sit amet eleifend pede libero quis orci. Nullam molestie nibh in lectus.\n\nPellentesque at nulla. Suspendisse potenti. Cras in purus eu magna vulputate luctus."
    },
    {
      "id": "68",
      "type": "expenses",
      "date": "8/3/2023",
      "amount": 43285468,
      "category": "문화생활",
      "asset": "현금",
      "content": "Cum sociis natoque penatibus et magnis dis parturient montes, nascetur ridiculus mus. Vivamus vestibulum sagittis sapien. Cum sociis natoque penatibus et magnis dis parturient montes, nascetur ridiculus mus.\n\nEtiam vel augue. Vestibulum rutrum rutrum neque. Aenean auctor gravida sem."
    },
    {
      "id": "69",
      "type": "expenses",
      "date": "1/9/2024",
      "amount": 82760854,
      "category": "문화생활",
      "asset": "국민은행",
      "content": "In quis justo. Maecenas rhoncus aliquam lacus. Morbi quis tortor id nulla ultrices aliquet.\n\nMaecenas leo odio, condimentum id, luctus nec, molestie sed, justo. Pellentesque viverra pede ac diam. Cras pellentesque volutpat dui."
    },
    {
      "id": "70",
      "type": "income",
      "date": "7/9/2023",
      "amount": 10941619,
      "category": "부모님",
      "asset": "우리은행",
      "content": "Fusce posuere felis sed lacus. Morbi sem mauris, laoreet ut, rhoncus aliquet, pulvinar sed, nisl. Nunc rhoncus dui vel sem.\n\nSed sagittis. Nam congue, risus semper porta volutpat, quam pede lobortis ligula, sit amet eleifend pede libero quis orci. Nullam molestie nibh in lectus."
    },
    {
      "id": "71",
      "type": "expenses",
      "date": "7/3/2023",
      "amount": 63463534,
      "category": "교통/차량",
      "asset": "현금",
      "content": "Praesent id massa id nisl venenatis lacinia. Aenean sit amet justo. Morbi ut odio."
    },
    {
      "id": "72",
      "type": "income",
      "date": "4/11/2024",
      "amount": 13076612,
      "category": "마트/편의점",
      "asset": "현금",
      "content": "Aenean lectus. Pellentesque eget nunc. Donec quis orci eget orci vehicula condimentum."
    },
    {
      "id": "73",
      "type": "income",
      "date": "11/28/2023",
      "amount": 17117961,
      "category": "경조사/회비",
      "asset": "국민은행",
      "content": "In sagittis dui vel nisl. Duis ac nibh. Fusce lacus purus, aliquet at, feugiat non, pretium quis, lectus."
    },
    {
      "id": "74",
      "type": "income",
      "date": "9/13/2023",
      "amount": 13821776,
      "category": "교통/차량",
      "asset": "국민은행",
      "content": "In hac habitasse platea dictumst. Etiam faucibus cursus urna. Ut tellus.\n\nNulla ut erat id mauris vulputate elementum. Nullam varius. Nulla facilisi."
    },
    {
      "id": "75",
      "type": "income",
      "date": "5/29/2024",
      "amount": 31922815,
      "category": "문화생활",
      "asset": "국민은행",
      "content": "Cras mi pede, malesuada in, imperdiet et, commodo vulputate, justo. In blandit ultrices enim. Lorem ipsum dolor sit amet, consectetuer adipiscing elit.\n\nProin interdum mauris non ligula pellentesque ultrices. Phasellus id sapien in sapien iaculis congue. Vivamus metus arcu, adipiscing molestie, hendrerit at, vulputate vitae, nisl."
    },
    {
      "id": "76",
      "type": "expenses",
      "date": "8/25/2023",
      "amount": 53652227,
      "category": "식비",
      "asset": "우리은행",
      "content": "Fusce consequat. Nulla nisl. Nunc nisl.\n\nDuis bibendum, felis sed interdum venenatis, turpis enim blandit mi, in porttitor pede justo eu massa. Donec dapibus. Duis at velit eu est congue elementum."
    },
    {
      "id": "77",
      "type": "expenses",
      "date": "6/14/2023",
      "amount": 36690097,
      "category": "패션/미용",
      "asset": "현금",
      "content": "Maecenas tristique, est et tempus semper, est quam pharetra magna, ac consequat metus sapien ut nunc. Vestibulum ante ipsum primis in faucibus orci luctus et ultrices posuere cubilia Curae; Mauris viverra diam vitae quam. Suspendisse potenti.\n\nNullam porttitor lacus at turpis. Donec posuere metus vitae ipsum. Aliquam non mauris."
    },
    {
      "id": "78",
      "type": "income",
      "date": "4/14/2024",
      "amount": 42880408,
      "category": "문화생활",
      "asset": "우리은행",
      "content": "Vestibulum quam sapien, varius ut, blandit non, interdum in, ante. Vestibulum ante ipsum primis in faucibus orci luctus et ultrices posuere cubilia Curae; Duis faucibus accumsan odio. Curabitur convallis.\n\nDuis consequat dui nec nisi volutpat eleifend. Donec ut dolor. Morbi vel lectus in quam fringilla rhoncus."
    },
    {
      "id": "79",
      "type": "income",
      "date": "2/7/2024",
      "amount": 11823677,
      "category": "기타",
      "asset": "국민은행",
      "content": "Praesent id massa id nisl venenatis lacinia. Aenean sit amet justo. Morbi ut odio."
    },
    {
      "id": "80",
      "type": "income",
      "date": "2/7/2024",
      "amount": 75678753,
      "category": "생활용품",
      "asset": "우리은행",
      "content": "Duis bibendum. Morbi non quam nec dui luctus rutrum. Nulla tellus.\n\nIn sagittis dui vel nisl. Duis ac nibh. Fusce lacus purus, aliquet at, feugiat non, pretium quis, lectus."
    },
    {
      "id": "81",
      "type": "income",
      "date": "2/25/2024",
      "amount": 57631074,
      "category": "마트/편의점",
      "asset": "현금",
      "content": "Morbi porttitor lorem id ligula. Suspendisse ornare consequat lectus. In est risus, auctor sed, tristique in, tempus sit amet, sem."
    },
    {
      "id": "82",
      "type": "income",
      "date": "8/6/2023",
      "amount": 72025861,
      "category": "패션/미용",
      "asset": "우리은행",
      "content": "Quisque id justo sit amet sapien dignissim vestibulum. Vestibulum ante ipsum primis in faucibus orci luctus et ultrices posuere cubilia Curae; Nulla dapibus dolor vel est. Donec odio justo, sollicitudin ut, suscipit a, feugiat et, eros."
    },
    {
      "id": "83",
      "type": "expenses",
      "date": "10/10/2023",
      "amount": 39587619,
      "category": "교육",
      "asset": "국민은행",
      "content": "Curabitur in libero ut massa volutpat convallis. Morbi odio odio, elementum eu, interdum eu, tincidunt in, leo. Maecenas pulvinar lobortis est.\n\nPhasellus sit amet erat. Nulla tempus. Vivamus in felis eu sapien cursus vestibulum."
    },
    {
      "id": "84",
      "type": "expenses",
      "date": "10/10/2023",
      "amount": 76515333,
      "category": "식비",
      "asset": "국민은행",
      "content": "Integer tincidunt ante vel ipsum. Praesent blandit lacinia erat. Vestibulum sed magna at nunc commodo placerat.\n\nPraesent blandit. Nam nulla. Integer pede justo, lacinia eget, tincidunt eget, tempus vel, pede."
    },
    {
      "id": "85",
      "type": "expenses",
      "date": "1/29/2024",
      "amount": 73938764,
      "category": "마트/편의점",
      "asset": "현금",
      "content": "Mauris enim leo, rhoncus sed, vestibulum sit amet, cursus id, turpis. Integer aliquet, massa id lobortis convallis, tortor risus dapibus augue, vel accumsan tellus nisi eu orci. Mauris lacinia sapien quis libero.\n\nNullam sit amet turpis elementum ligula vehicula consequat. Morbi a ipsum. Integer a nibh."
    },
    {
      "id": "86",
      "type": "income",
      "date": "4/7/2024",
      "amount": 66513033,
      "category": "문화생활",
      "asset": "현금",
      "content": "Duis bibendum, felis sed interdum venenatis, turpis enim blandit mi, in porttitor pede justo eu massa. Donec dapibus. Duis at velit eu est congue elementum.\n\nIn hac habitasse platea dictumst. Morbi vestibulum, velit id pretium iaculis, diam erat fermentum justo, nec condimentum neque sapien placerat ante. Nulla justo."
    },
    {
      "id": "87",
      "type": "income",
      "date": "2/23/2024",
      "amount": 26662911,
      "category": "기타",
      "asset": "국민은행",
      "content": "Curabitur gravida nisi at nibh. In hac habitasse platea dictumst. Aliquam augue quam, sollicitudin vitae, consectetuer eget, rutrum at, lorem.\n\nInteger tincidunt ante vel ipsum. Praesent blandit lacinia erat. Vestibulum sed magna at nunc commodo placerat."
    },
    {
      "id": "88",
      "type": "expenses",
      "date": "7/21/2023",
      "amount": 93185067,
      "category": "문화생활",
      "asset": "우리은행",
      "content": "Maecenas ut massa quis augue luctus tincidunt. Nulla mollis molestie lorem. Quisque ut erat.\n\nCurabitur gravida nisi at nibh. In hac habitasse platea dictumst. Aliquam augue quam, sollicitudin vitae, consectetuer eget, rutrum at, lorem."
    },
    {
      "id": "89",
      "type": "income",
      "date": "2/29/2024",
      "amount": 86136713,
      "category": "교통/차량",
      "asset": "현금",
      "content": "Proin interdum mauris non ligula pellentesque ultrices. Phasellus id sapien in sapien iaculis congue. Vivamus metus arcu, adipiscing molestie, hendrerit at, vulputate vitae, nisl."
    },
    {
      "id": "90",
      "type": "expenses",
      "date": "1/3/2024",
      "amount": 43925537,
      "category": "문화생활",
      "asset": "현금",
      "content": "Duis bibendum, felis sed interdum venenatis, turpis enim blandit mi, in porttitor pede justo eu massa. Donec dapibus. Duis at velit eu est congue elementum."
    },
    {
      "id": "91",
      "type": "expenses",
      "date": "7/24/2023",
      "amount": 92958583,
      "category": "패션/미용",
      "asset": "우리은행",
      "content": "Sed ante. Vivamus tortor. Duis mattis egestas metus.\n\nAenean fermentum. Donec ut mauris eget massa tempor convallis. Nulla neque libero, convallis eget, eleifend luctus, ultricies eu, nibh."
    },
    {
      "id": "92",
      "type": "expenses",
      "date": "6/27/2023",
      "amount": 11233164,
      "category": "기타",
      "asset": "우리은행",
      "content": "Suspendisse potenti. In eleifend quam a odio. In hac habitasse platea dictumst."
    },
    {
      "id": "93",
      "type": "expenses",
      "date": "1/12/2024",
      "amount": 72893667,
      "category": "문화생활",
      "asset": "국민은행",
      "content": "Cras mi pede, malesuada in, imperdiet et, commodo vulputate, justo. In blandit ultrices enim. Lorem ipsum dolor sit amet, consectetuer adipiscing elit.\n\nProin interdum mauris non ligula pellentesque ultrices. Phasellus id sapien in sapien iaculis congue. Vivamus metus arcu, adipiscing molestie, hendrerit at, vulputate vitae, nisl."
    },
    {
      "id": "94",
      "type": "expenses",
      "date": "6/11/2023",
      "amount": 78903442,
      "category": "교통/차량",
      "asset": "우리은행",
      "content": "Fusce posuere felis sed lacus. Morbi sem mauris, laoreet ut, rhoncus aliquet, pulvinar sed, nisl. Nunc rhoncus dui vel sem.\n\nSed sagittis. Nam congue, risus semper porta volutpat, quam pede lobortis ligula, sit amet eleifend pede libero quis orci. Nullam molestie nibh in lectus."
    },
    {
      "id": "95",
      "type": "expenses",
      "date": "5/1/2024",
      "amount": 22499904,
      "category": "마트/편의점",
      "asset": "우리은행",
      "content": "Curabitur gravida nisi at nibh. In hac habitasse platea dictumst. Aliquam augue quam, sollicitudin vitae, consectetuer eget, rutrum at, lorem."
    },
    {
      "id": "96",
      "type": "expenses",
      "date": "6/5/2024",
      "amount": 95209334,
      "category": "기타",
      "asset": "은행",
      "content": "Fusce posuere felis sed lacus. Morbi sem mauris, laoreet ut, rhoncus aliquet, pulvinar sed, nisl. Nunc rhoncus dui vel sem.\n\nSed sagittis. Nam congue, risus semper porta volutpat, quam pede lobortis ligula, sit amet eleifend pede libero quis orci. Nullam molestie nibh in lectus."
    },
    {
      "id": "97",
      "type": "income",
      "date": "2023-08-09",
      "amount": 71029276,
      "category": "건강",
      "asset": "카드",
      "content": "Integer tincidunt ante vel ipsum. Praesent blandit lacinia erat. Vestibulum sed magna at nunc commod ..."
    },
    {
      "id": "98",
      "type": "expenses",
      "date": "11/19/2023",
      "amount": 30450406,
      "category": "식비",
      "asset": "현금",
      "content": "Morbi porttitor lorem id ligula. Suspendisse ornare consequat lectus. In est risus, auctor sed, tristique in, tempus sit amet, sem.\n\nFusce consequat. Nulla nisl. Nunc nisl."
    },
    {
      "id": "99",
      "type": "expenses",
      "date": "1/18/2024",
      "amount": 91255184,
      "category": "마트/편의점",
      "asset": "우리은행",
      "content": "Suspendisse potenti. In eleifend quam a odio. In hac habitasse platea dictumst.\n\nMaecenas ut massa quis augue luctus tincidunt. Nulla mollis molestie lorem. Quisque ut erat."
    },
    {
      "id": "100",
      "type": "income",
      "date": "5/18/2024",
      "amount": 28351625,
      "category": "생활용품",
      "asset": "현금",
      "content": "In hac habitasse platea dictumst. Morbi vestibulum, velit id pretium iaculis, diam erat fermentum justo, nec condimentum neque sapien placerat ante. Nulla justo."
    },
    {
      "id": 1718237825031,
      "type": "income",
      "date": "",
      "amount": "",
      "category": "",
      "asset": "",
      "content": ""
    },
    {
      "id": 1718237893675,
      "type": "income",
      "date": "",
      "amount": "",
      "category": "",
      "asset": "",
      "content": ""
    },
    {
      "id": 1718237894608,
      "type": "income",
      "date": "",
      "amount": "",
      "category": "",
      "asset": "",
      "content": ""
    },
    {
      "id": 1718237903284,
      "type": "income",
      "date": "",
      "amount": "",
      "category": "",
      "asset": "",
      "content": ""
    },
    {
      "id": 1718237916645,
      "type": "income",
      "date": "",
      "amount": "",
      "category": "",
      "asset": "",
      "content": ""
    },
    {
      "id": 1718237917121,
      "type": "income",
      "date": "",
      "amount": "",
      "category": "",
      "asset": "",
      "content": ""
    },
    {
      "id": 1718237918177,
      "type": "income",
      "date": "",
      "amount": "",
      "category": "",
      "asset": "",
      "content": ""
    },
    {
      "id": 1718237918781,
      "type": "income",
      "date": "",
      "amount": "",
      "category": "",
      "asset": "",
      "content": ""
    },
    {
      "id": 1718237919169,
      "type": "income",
      "date": "",
      "amount": "",
      "category": "",
      "asset": "",
      "content": ""
    }
  ]
}